kelian/__init__.py
kelian/average_time.py
kelian/encryption.py
kelian/loading_bar.py
kelian/system.py
kelian/utils.py
kelian/data/__init__.py
kelian/data/encryption/__init__.py
kelian/data/encryption/manga.py
kelian-0.1.9.dist-info/LICENSE.txt
kelian-0.1.9.dist-info/METADATA
kelian-0.1.9.dist-info/WHEEL
kelian-0.1.9.dist-info/top_level.txt
kelian-0.1.9.dist-info/RECORD
