Metadata-Version: 2.2
Name: kelian
Version: 0.1.9
Summary: Library of useful code snippets
Home-page: https://github.com/Game-K-Hack/kelian
Author: Kelian
Project-URL: Bug Tracker, https://github.com/Game-K-Hack/kelian/issues
Classifier: Programming Language :: Python :: 3
Classifier: License :: OSI Approved :: MIT License
Classifier: Operating System :: OS Independent
Requires-Python: >=3.11
License-File: LICENSE.txt
Requires-Dist: pywin32
Requires-Dist: WMI
Dynamic: author
Dynamic: classifier
Dynamic: description
Dynamic: description-content-type
Dynamic: home-page
Dynamic: project-url
Dynamic: requires-dist
Dynamic: requires-python
Dynamic: summary
